rteplayer_dl/__init__.py
rteplayer_dl/cli.py
rteplayer_dl/lib.py
rteplayer_dl/rteplayer.py
rteplayer_dl-0.0.4.dist-info/AUTHORS.rst
rteplayer_dl-0.0.4.dist-info/LICENSE
rteplayer_dl-0.0.4.dist-info/METADATA
rteplayer_dl-0.0.4.dist-info/WHEEL
rteplayer_dl-0.0.4.dist-info/entry_points.txt
rteplayer_dl-0.0.4.dist-info/top_level.txt
rteplayer_dl-0.0.4.dist-info/RECORD
