Metadata-Version: 2.1
Name: rteplayer-dl
Version: 0.0.4
Summary: Helpful python project to download videos from RTE Player.
Home-page: https://github.com/philroche/rteplayer_dl
Author: Phil Roche
Author-email: phil@tinyviking.ie
License: MIT license
Keywords: rteplayer_dl
Platform: UNKNOWN
Classifier: Development Status :: 2 - Pre-Alpha
Classifier: Intended Audience :: Developers
Classifier: License :: OSI Approved :: MIT License
Classifier: Natural Language :: English
Classifier: Programming Language :: Python :: 3.5
Classifier: Programming Language :: Python :: 3.6
Classifier: Programming Language :: Python :: 3.7
Requires-Dist: bs4
Requires-Dist: Click (>=6.0)
Requires-Dist: ffmpeg-python
Requires-Dist: lxml
Requires-Dist: requests
Requires-Dist: youtube-dl
